planes_around/__init__.py
planes_around/cli.py
planes_around/conf.py
planes_around/utils.py
planes_around-1.2.dist-info/DESCRIPTION.rst
planes_around-1.2.dist-info/METADATA
planes_around-1.2.dist-info/RECORD
planes_around-1.2.dist-info/WHEEL
planes_around-1.2.dist-info/entry_points.txt
planes_around-1.2.dist-info/metadata.json
planes_around-1.2.dist-info/top_level.txt
