Metadata-Version: 2.0
Name: planes-around
Version: 1.2
Summary: Get info about planes around the specified location using the OpenSky service.
Home-page: http://github.com/vladimir-vovk/planes-around
Author: Vladimir Vovk
Author-email: vladimir.vovk.at@gmail.com
License: MIT
Keywords: plane location opensky
Platform: UNKNOWN
Classifier: Development Status :: 4 - Beta
Classifier: Environment :: Console
Classifier: Intended Audience :: End Users/Desktop
Classifier: License :: OSI Approved :: MIT License
Classifier: Programming Language :: Python :: 3
Classifier: Programming Language :: Python :: 3.6
Classifier: Natural Language :: English
Classifier: Topic :: Utilities
Requires-Python: >=3
Requires-Dist: geopy
Requires-Dist: requests
Requires-Dist: folium
